AUTHORS.rst
CONTRIBUTING.rst
HISTORY.rst
LICENSE
MANIFEST.in
README.rst
setup.cfg
setup.py
jet/__init__.py
jet/jet.py
jet_python.egg-info/PKG-INFO
jet_python.egg-info/SOURCES.txt
jet_python.egg-info/dependency_links.txt
jet_python.egg-info/not-zip-safe
jet_python.egg-info/requires.txt
jet_python.egg-info/top_level.txt
test/test_jet.py