Metadata-Version: 1.1
Name: jet-python
Version: 0.1
Summary: Python Jet.com API Client
Home-page: https://github.com/fulfilio/jet-python
Author: Fulfil.IO Inc.
Author-email: tech-support@fulfil.io
License: MIT
Keywords: jet jet.com python
Platform: UNKNOWN
Classifier: Development Status :: 2 - Pre-Alpha
Classifier: Intended Audience :: Developers
Classifier: License :: OSI Approved :: MIT License
Classifier: Natural Language :: English
Classifier: Programming Language :: Python :: 2
Classifier: Programming Language :: Python :: 2.6
Classifier: Programming Language :: Python :: 2.7
Classifier: Programming Language :: Python :: 3
Classifier: Programming Language :: Python :: 3.3
Classifier: Programming Language :: Python :: Implementation :: PyPy
